wikisearch/__init__.py
wikisearch/article.py
wikisearch/wikisearcher.py
wikisearch/wikiutil/__init__.py
wikisearch/wikiutil/report.py
wikisearch/wikiutil/wikiutil.py
wikipedia_searcher-0.0.5.dist-info/LICENSE.txt
wikipedia_searcher-0.0.5.dist-info/METADATA
wikipedia_searcher-0.0.5.dist-info/WHEEL
wikipedia_searcher-0.0.5.dist-info/top_level.txt
wikipedia_searcher-0.0.5.dist-info/RECORD
