Metadata-Version: 2.1
Name: wikipedia-searcher
Version: 0.0.5
Summary: A script that scrapes wikipedia
Home-page: UNKNOWN
Author: Ziegfred Zorrilla
Author-email: ziegfredzorrilla23@gmail.com
License: UNKNOWN
Platform: UNKNOWN
Classifier: Programming Language :: Python :: 3
Classifier: License :: OSI Approved :: MIT License
Classifier: Operating System :: OS Independent
Requires-Python: >=3.9
License-File: LICENSE.txt
Requires-Dist: beautifulsoup4 (==4.9.3)
Requires-Dist: certifi (==2021.5.30)
Requires-Dist: chardet (==4.0.0)
Requires-Dist: idna (==2.10)
Requires-Dist: lxml (==4.6.3)
Requires-Dist: more-itertools (==8.8.0)
Requires-Dist: requests (==2.25.1)
Requires-Dist: soupsieve (==2.2.1)
Requires-Dist: urllib3 (==1.26.6)
